booking_host_api/__init__.py
booking_host_api/base.py
booking_host_api/booking.py
booking_host_api/booking_locators.py
booking_host_api/config.py
booking_host_api-0.0.1.dist-info/METADATA
booking_host_api-0.0.1.dist-info/WHEEL
booking_host_api-0.0.1.dist-info/licenses/LICENSE
booking_host_api-0.0.1.dist-info/RECORD
