Metadata-Version: 2.4
Name: booking-host-api
Version: 0.0.1
Summary: Simple native Booking.com API wrapper
Author-email: kaxcheg <kaxcheg@gmail.com>
License: MIT License
License-File: LICENSE
Keywords: API,booking
Classifier: Operating System :: OS Independent
Classifier: Programming Language :: Python :: 3
Requires-Python: >=3.12.5
Requires-Dist: requests>=2.32.3
Requires-Dist: selenium>=4.28.1
